unienv_maniskill/__init__.py
unienv_maniskill/wrapper/maniskill_compat.py
unienv_maniskill-0.0.1a1.dist-info/METADATA
unienv_maniskill-0.0.1a1.dist-info/WHEEL
unienv_maniskill-0.0.1a1.dist-info/top_level.txt
unienv_maniskill-0.0.1a1.dist-info/RECORD
